AUTHORS.rst
CONTRIBUTING.rst
HISTORY.rst
LICENSE
MANIFEST.in
README.rst
setup.cfg
setup.py
docs/Makefile
docs/authors.rst
docs/conf.py
docs/contributing.rst
docs/history.rst
docs/index.rst
docs/installation.rst
docs/make.bat
docs/readme.rst
docs/usage.rst
pymspack.egg-info/PKG-INFO
pymspack.egg-info/SOURCES.txt
pymspack.egg-info/dependency_links.txt
pymspack.egg-info/not-zip-safe
pymspack.egg-info/top_level.txt
src/__init__.py
src/ext.c
src/ext.pxd
src/ext.pyx
tests/__init__.py
tests/test_pymspack.py
tests/data/000.cab