Metadata-Version: 1.1
Name: pymspack
Version: 0.2.0
Summary: Python bindings to libmspack
Home-page: https://github.com/gcrahay/pymspack
Author: Gaetan Crahay
Author-email: gaetan@crahay.eu
License: BSD license
Keywords: pymspack
Platform: UNKNOWN
Classifier: Development Status :: 2 - Pre-Alpha
Classifier: Intended Audience :: Developers
Classifier: License :: OSI Approved :: BSD License
Classifier: Natural Language :: English
Classifier: Programming Language :: Python :: 2
Classifier: Programming Language :: Python :: 2.7
Classifier: Programming Language :: Python :: 3
Classifier: Programming Language :: Python :: 3.5
